download_sorter/__init__.py
download_sorter/download_sort.py
download_sorter-0.1.1.dist-info/METADATA
download_sorter-0.1.1.dist-info/WHEEL
download_sorter-0.1.1.dist-info/RECORD
