Metadata-Version: 2.1
Name: download-sorter
Version: 0.1.1
Summary: Organizes the files in your Downloads folder based on their file extensions. The module moves files into predefined folders according to a configuration file, making it easier to find and manage your downloaded files.
License: MIT
Author: DJ Stomp
Author-email: 85457381+DJStompZone@users.noreply.github.com
Requires-Python: >=3.8,<4.0
Classifier: License :: OSI Approved :: MIT License
Classifier: Programming Language :: Python :: 3
Classifier: Programming Language :: Python :: 3.8
Classifier: Programming Language :: Python :: 3.9
Classifier: Programming Language :: Python :: 3.10
Classifier: Programming Language :: Python :: 3.11
